<?xml version="1.0" encoding="utf-8"?>
<warpconfig version="1.0" profile="default">
	<profile name="default">
		<map id="1" display="1">
			<warp method="perspectivebilinear" width="2" height="2" brightness="1" srcAreaX1="-1" srcAreaX2="-1" srcAreaY1="-1" srcAreaY2="-1" resolution="16" linear="0" adaptive="0">
				<controlpoint x="0" y="0"/>
				<controlpoint x="0" y="1"/>
				<controlpoint x="1" y="0"/>
				<controlpoint x="1" y="1"/>
				<corner x="0.223632813" y="0.266927093"/>
				<corner x="0.668749988" y="0.217777774"/>
				<corner x="0.659179688" y="0.592447937"/>
				<corner x="0.254882813" y="0.62890625"/>
			</warp>
		</map>
		<map id="2" display="1">
			<warp method="perspectivebilinear" width="2" height="2" brightness="1" srcAreaX1="-1" srcAreaX2="-1" srcAreaY1="-1" srcAreaY2="-1" resolution="16" linear="0" adaptive="0">
				<controlpoint x="0" y="0"/>
				<controlpoint x="0" y="1"/>
				<controlpoint x="1" y="0"/>
				<controlpoint x="1" y="1"/>
				<corner x="0.0581250004" y="0.374444455"/>
				<corner x="0.213750005" y="0.362222224"/>
				<corner x="0.245138884" y="0.67958951"/>
				<corner x="0.0731249973" y="0.682222247"/>
			</warp>
		</map>
		<map id="3" display="1">
			<warp method="perspectivebilinear" width="2" height="2" brightness="1" srcAreaX1="-842150451" srcAreaX2="-842150451" srcAreaY1="-842150451" srcAreaY2="-842150451" resolution="16" linear="0" adaptive="0">
				<controlpoint x="0" y="0"/>
				<controlpoint x="0" y="1"/>
				<controlpoint x="1" y="0"/>
				<controlpoint x="1" y="1"/>
				<corner x="0.741874993" y="0.105555557"/>
				<corner x="0.954999983" y="0.119999997"/>
				<corner x="0.980000019" y="0.705555558"/>
				<corner x="0.732500017" y="0.576666653"/>
			</warp>
		</map>
	</profile>
</warpconfig>

